dap/__init__.py
dap/__main__.py
dap/api.py
dap/concurrency.py
dap/counted.py
dap/dap_error.py
dap/dap_types.py
dap/log.py
dap/networking.py
dap/payload.py
dap/py.typed
dap/retry_options.py
dap/timer.py
dap/timestamp.py
dap/tracking.py
dap/ui.py
dap/actions/__init__.py
dap/actions/download_incremental.py
dap/actions/download_schema.py
dap/actions/download_snapshot.py
dap/actions/drop_db.py
dap/actions/init_db.py
dap/actions/list_tables.py
dap/actions/sync_db.py
dap/commands/__init__.py
dap/commands/command_group.py
dap/commands/commands.py
dap/commands/global_options.py
dap/integration/__init__.py
dap/integration/base_connection.py
dap/integration/connection.py
dap/integration/database.py
dap/integration/database_errors.py
dap/replicator/__init__.py
dap/replicator/canvas.py
dap/replicator/canvas_logs.py
dap/replicator/catalog.py
dap/replicator/meta_schema.py
dap/replicator/sql.py
dap/replicator/sql_metatable_handler.py
dap/replicator/sql_op.py
dap/replicator/sql_op_drop.py
dap/replicator/sql_op_init.py
dap/replicator/sql_op_sync.py
dap/version_upgrade/__init__.py
dap/version_upgrade/db_version_upgrader.py
dap/version_upgrade/mssql_0_to_1.sql
dap/version_upgrade/mysql_0_to_1.sql
dap/version_upgrade/postgresql_0_to_1.sql
instructure_dap_client-2.1.0.dist-info/licenses/LICENSE
instructure_dap_client-2.1.0.dist-info/METADATA
instructure_dap_client-2.1.0.dist-info/WHEEL
instructure_dap_client-2.1.0.dist-info/entry_points.txt
instructure_dap_client-2.1.0.dist-info/top_level.txt
instructure_dap_client-2.1.0.dist-info/zip-safe
instructure_dap_client-2.1.0.dist-info/RECORD
